loadforecasting_models/__init__.py
loadforecasting_models/helpers.py
loadforecasting_models/knn.py
loadforecasting_models/lstm.py
loadforecasting_models/normalizer.py
loadforecasting_models/perfect.py
loadforecasting_models/persistence.py
loadforecasting_models/transformer.py
loadforecasting_models/transformer_full.py
loadforecasting_models/xlstm.py
loadforecasting_models-0.3.1.dist-info/METADATA
loadforecasting_models-0.3.1.dist-info/WHEEL
loadforecasting_models-0.3.1.dist-info/top_level.txt
loadforecasting_models-0.3.1.dist-info/RECORD
