Metadata-Version: 2.4
Name: loadforecasting_models
Version: 0.3.1
Summary: Package, containing multiple state-of-the-art forecasting models.
Author-email: Lukas Moosbrugger <molu@fhv.at>
License-Expression: MIT
Classifier: Programming Language :: Python :: 3
Classifier: Operating System :: OS Independent
Requires-Python: >=3.9
Requires-Dist: torch
Requires-Dist: scikit-learn
Requires-Dist: xlstm
Requires-Dist: optuna
